nluanalyzer/__init__.py
nluanalyzer/converter.py
nluanalyzer/nluanalyzer.py
nluanalizer-1.0.2.dist-info/LICENSE.txt
nluanalizer-1.0.2.dist-info/METADATA
nluanalizer-1.0.2.dist-info/WHEEL
nluanalizer-1.0.2.dist-info/entry_points.txt
nluanalizer-1.0.2.dist-info/top_level.txt
nluanalizer-1.0.2.dist-info/RECORD
