Metadata-Version: 2.1
Name: nluanalizer
Version: 1.0.2
Summary: Natural Language Tool to Extract Features from Intents Dataset.
Home-page: https://github.com/AlvArranzDom/nluanalyzer
Author: Alvaro Arranz
Author-email: alvaro.arranz@outlook.com
License: MIT
Keywords: nlu natural language spanish
Platform: UNKNOWN
Classifier: Development Status :: 5 - Production/Stable
Classifier: Intended Audience :: Developers
Classifier: Topic :: Software Development :: Build Tools
Classifier: License :: OSI Approved :: MIT License
Classifier: Natural Language :: Spanish
Classifier: Programming Language :: Python :: 2
Classifier: Programming Language :: Python :: 2.7
Classifier: Programming Language :: Python :: 3
Classifier: Programming Language :: Python :: 3.4
Classifier: Programming Language :: Python :: 3.5
Classifier: Programming Language :: Python :: 3.6
Classifier: Programming Language :: Python :: 3.7
Requires-Python: >=3
Requires-Dist: wheel (==0.34.2)
Requires-Dist: nltk (==3.4.5)
Requires-Dist: spacy (==2.2.4)
Requires-Dist: docopt (==0.6.2)
Requires-Dist: numpy (==1.17.4)
Requires-Dist: pandas (==0.25.3)
Requires-Dist: textacy (==0.10.0)
Requires-Dist: scikit-learn (==0.23.1)
